mseep_openderisk-0.1.0.dist-info/licenses/LICENSE
packages/__init__.py
packages/derisk-app/__init__.py
packages/derisk-app/src/__init__.py
packages/derisk-app/src/derisk_app/__init__.py
packages/derisk-app/src/derisk_app/_cli.py
packages/derisk-app/src/derisk_app/base.py
packages/derisk-app/src/derisk_app/component_configs.py
packages/derisk-app/src/derisk_app/config.py
packages/derisk-app/src/derisk_app/derisk_server.py
packages/derisk-app/src/derisk_app/initialization/__init__.py
packages/derisk-app/src/derisk_app/initialization/db_model_initialization.py
packages/derisk-app/src/derisk_app/initialization/embedding_component.py
packages/derisk-app/src/derisk_app/initialization/scheduler.py
packages/derisk-app/src/derisk_app/initialization/serve_initialization.py
packages/derisk-app/src/derisk_app/knowledge/__init__.py
packages/derisk-app/src/derisk_app/knowledge/api.py
packages/derisk-app/src/derisk_app/knowledge/service.py
packages/derisk-app/src/derisk_app/knowledge/_cli/__init__.py
packages/derisk-app/src/derisk_app/knowledge/_cli/knowledge_cli.py
packages/derisk-app/src/derisk_app/knowledge/_cli/knowledge_client.py
packages/derisk-app/src/derisk_app/knowledge/request/__init__.py
packages/derisk-app/src/derisk_app/knowledge/request/request.py
packages/derisk-app/src/derisk_app/knowledge/request/response.py
packages/derisk-app/src/derisk_app/openapi/__init__.py
packages/derisk-app/src/derisk_app/openapi/api_view_model.py
packages/derisk-app/src/derisk_app/openapi/base.py
packages/derisk-app/src/derisk_app/openapi/editor_view_model.py
packages/derisk-app/src/derisk_app/openapi/api_v1/__init__.py
packages/derisk-app/src/derisk_app/openapi/api_v1/api_v1.py
packages/derisk-app/src/derisk_app/openapi/api_v1/editor/__init__.py
packages/derisk-app/src/derisk_app/openapi/api_v1/editor/api_editor_v1.py
packages/derisk-app/src/derisk_app/openapi/api_v1/editor/service.py
packages/derisk-app/src/derisk_app/openapi/api_v1/editor/sql_editor.py
packages/derisk-app/src/derisk_app/openapi/api_v1/editor/_chat_history/__init__.py
mseep_openderisk-0.1.0.dist-info/METADATA
mseep_openderisk-0.1.0.dist-info/WHEEL
mseep_openderisk-0.1.0.dist-info/top_level.txt
mseep_openderisk-0.1.0.dist-info/RECORD
